arsoscreen/__init__.py
arsoscreen-0.0.1.dist-info/METADATA
arsoscreen-0.0.1.dist-info/WHEEL
arsoscreen-0.0.1.dist-info/top_level.txt
arsoscreen-0.0.1.dist-info/RECORD
