Metadata-Version: 2.1
Name: arsoscreen
Version: 0.0.1
Summary: arsoscreen.save("filename with extension", "extension")
Home-page: UNKNOWN
License: UNKNOWN
Platform: UNKNOWN
Requires-Dist: pillow
